terraflow-0.0.2.dist-info/DESCRIPTION.rst
terraflow-0.0.2.dist-info/METADATA
terraflow-0.0.2.dist-info/RECORD
terraflow-0.0.2.dist-info/WHEEL
terraflow-0.0.2.dist-info/entry_points.txt
terraflow-0.0.2.dist-info/metadata.json
terraflow-0.0.2.dist-info/top_level.txt
test/__init__.py
test/test_commands.py
test/test_configuration.py
tf/__init__.py
tf/args.py
tf/colors.py
tf/tf.py
