Metadata-Version: 2.0
Name: terraflow
Version: 0.0.2
Summary: A Terraform wrapper script for managing stacks and environments.
Home-page: https://github.com/micahlmartin/terraflow
Author: Micah Martin
Author-email: micahlmartin@gmail.com
License: MIT
Keywords: terraform iac
Platform: UNKNOWN
Classifier: Development Status :: 3 - Alpha
Classifier: Intended Audience :: Developers
Classifier: Topic :: Software Development :: Build Tools
Classifier: License :: OSI Approved :: MIT License
Classifier: Programming Language :: Python :: 2
Classifier: Programming Language :: Python :: 2.6
Classifier: Programming Language :: Python :: 2.7
Classifier: Programming Language :: Python :: 3
Classifier: Programming Language :: Python :: 3.3
Classifier: Programming Language :: Python :: 3.4
Classifier: Programming Language :: Python :: 3.5
